{
  "timestamp": "2026-04-25T21:33:39.890091+00:00",
  "space_weather": {
    "timestamp": "2026-04-25T21:33:39.577911+00:00",
    "kp_current": 0.47,
    "kp_forecast_max_24h": 0,
    "solar_flux": 3.559234301064862e-06,
    "flare_class": "M",
    "storm_probability": {
      "G1": 0,
      "G2": 0,
      "G3": 0
    },
    "kp_forecast": []
  },
  "grid_stress": [
    {
      "grid_stress_score": 5.41,
      "geo_component": 0.21,
      "solar_component": 1.2,
      "energy_component": 4.0,
      "risk_level": "HIGH",
      "kp_current": 0.47,
      "kp_forecast_max": 0,
      "flare_class": "M",
      "location": "Västerås",
      "country_code": "se",
      "z_score": -3.01,
      "label": "Rischio rete elevato a Västerås: combinazione domanda anomala + perturbazione magnetica (Kp=0.5)"
    },
    {
      "grid_stress_score": 5.41,
      "geo_component": 0.21,
      "solar_component": 1.2,
      "energy_component": 4.0,
      "risk_level": "HIGH",
      "kp_current": 0.47,
      "kp_forecast_max": 0,
      "flare_class": "M",
      "location": "Vasteras",
      "country_code": "se",
      "z_score": -3.02,
      "label": "Rischio rete elevato a Vasteras: combinazione domanda anomala + perturbazione magnetica (Kp=0.5)"
    },
    {
      "grid_stress_score": 5.41,
      "geo_component": 0.21,
      "solar_component": 1.2,
      "energy_component": 4.0,
      "risk_level": "HIGH",
      "kp_current": 0.47,
      "kp_forecast_max": 0,
      "flare_class": "M",
      "location": "Tromsoe",
      "country_code": "no",
      "z_score": -3.51,
      "label": "Rischio rete elevato a Tromsoe: combinazione domanda anomala + perturbazione magnetica (Kp=0.5)"
    },
    {
      "grid_stress_score": 5.41,
      "geo_component": 0.21,
      "solar_component": 1.2,
      "energy_component": 4.0,
      "risk_level": "HIGH",
      "kp_current": 0.47,
      "kp_forecast_max": 0,
      "flare_class": "M",
      "location": "Tampere",
      "country_code": "fi",
      "z_score": -3.17,
      "label": "Rischio rete elevato a Tampere: combinazione domanda anomala + perturbazione magnetica (Kp=0.5)"
    },
    {
      "grid_stress_score": 5.41,
      "geo_component": 0.21,
      "solar_component": 1.2,
      "energy_component": 4.0,
      "risk_level": "HIGH",
      "kp_current": 0.47,
      "kp_forecast_max": 0,
      "flare_class": "M",
      "location": "Charlotte",
      "country_code": "us",
      "z_score": 4.14,
      "label": "Rischio rete elevato a Charlotte: combinazione domanda anomala + perturbazione magnetica (Kp=0.5)"
    },
    {
      "grid_stress_score": 5.41,
      "geo_component": 0.21,
      "solar_component": 1.2,
      "energy_component": 4.0,
      "risk_level": "HIGH",
      "kp_current": 0.47,
      "kp_forecast_max": 0,
      "flare_class": "M",
      "location": "Miami",
      "country_code": "us",
      "z_score": 3.93,
      "label": "Rischio rete elevato a Miami: combinazione domanda anomala + perturbazione magnetica (Kp=0.5)"
    },
    {
      "grid_stress_score": 5.41,
      "geo_component": 0.21,
      "solar_component": 1.2,
      "energy_component": 4.0,
      "risk_level": "HIGH",
      "kp_current": 0.47,
      "kp_forecast_max": 0,
      "flare_class": "M",
      "location": "Tampa",
      "country_code": "us",
      "z_score": 4.21,
      "label": "Rischio rete elevato a Tampa: combinazione domanda anomala + perturbazione magnetica (Kp=0.5)"
    },
    {
      "grid_stress_score": 5.41,
      "geo_component": 0.21,
      "solar_component": 1.2,
      "energy_component": 4.0,
      "risk_level": "HIGH",
      "kp_current": 0.47,
      "kp_forecast_max": 0,
      "flare_class": "M",
      "location": "Orlando",
      "country_code": "us",
      "z_score": 4.38,
      "label": "Rischio rete elevato a Orlando: combinazione domanda anomala + perturbazione magnetica (Kp=0.5)"
    },
    {
      "grid_stress_score": 5.41,
      "geo_component": 0.21,
      "solar_component": 1.2,
      "energy_component": 4.0,
      "risk_level": "HIGH",
      "kp_current": 0.47,
      "kp_forecast_max": 0,
      "flare_class": "M",
      "location": "Jacksonville",
      "country_code": "us",
      "z_score": 4.33,
      "label": "Rischio rete elevato a Jacksonville: combinazione domanda anomala + perturbazione magnetica (Kp=0.5)"
    },
    {
      "grid_stress_score": 5.41,
      "geo_component": 0.21,
      "solar_component": 1.2,
      "energy_component": 4.0,
      "risk_level": "HIGH",
      "kp_current": 0.47,
      "kp_forecast_max": 0,
      "flare_class": "M",
      "location": "Houston",
      "country_code": "us",
      "z_score": 4.49,
      "label": "Rischio rete elevato a Houston: combinazione domanda anomala + perturbazione magnetica (Kp=0.5)"
    },
    {
      "grid_stress_score": 5.41,
      "geo_component": 0.21,
      "solar_component": 1.2,
      "energy_component": 4.0,
      "risk_level": "HIGH",
      "kp_current": 0.47,
      "kp_forecast_max": 0,
      "flare_class": "M",
      "location": "Dallas",
      "country_code": "us",
      "z_score": 4.17,
      "label": "Rischio rete elevato a Dallas: combinazione domanda anomala + perturbazione magnetica (Kp=0.5)"
    },
    {
      "grid_stress_score": 5.41,
      "geo_component": 0.21,
      "solar_component": 1.2,
      "energy_component": 4.0,
      "risk_level": "HIGH",
      "kp_current": 0.47,
      "kp_forecast_max": 0,
      "flare_class": "M",
      "location": "Austin",
      "country_code": "us",
      "z_score": 4.27,
      "label": "Rischio rete elevato a Austin: combinazione domanda anomala + perturbazione magnetica (Kp=0.5)"
    },
    {
      "grid_stress_score": 5.41,
      "geo_component": 0.21,
      "solar_component": 1.2,
      "energy_component": 4.0,
      "risk_level": "HIGH",
      "kp_current": 0.47,
      "kp_forecast_max": 0,
      "flare_class": "M",
      "location": "San Antonio",
      "country_code": "us",
      "z_score": 3.93,
      "label": "Rischio rete elevato a San Antonio: combinazione domanda anomala + perturbazione magnetica (Kp=0.5)"
    },
    {
      "grid_stress_score": 5.41,
      "geo_component": 0.21,
      "solar_component": 1.2,
      "energy_component": 4.0,
      "risk_level": "HIGH",
      "kp_current": 0.47,
      "kp_forecast_max": 0,
      "flare_class": "M",
      "location": "Fort Worth",
      "country_code": "us",
      "z_score": 4.29,
      "label": "Rischio rete elevato a Fort Worth: combinazione domanda anomala + perturbazione magnetica (Kp=0.5)"
    },
    {
      "grid_stress_score": 5.41,
      "geo_component": 0.21,
      "solar_component": 1.2,
      "energy_component": 4.0,
      "risk_level": "HIGH",
      "kp_current": 0.47,
      "kp_forecast_max": 0,
      "flare_class": "M",
      "location": "El Paso",
      "country_code": "us",
      "z_score": 3.31,
      "label": "Rischio rete elevato a El Paso: combinazione domanda anomala + perturbazione magnetica (Kp=0.5)"
    },
    {
      "grid_stress_score": 5.41,
      "geo_component": 0.21,
      "solar_component": 1.2,
      "energy_component": 4.0,
      "risk_level": "HIGH",
      "kp_current": 0.47,
      "kp_forecast_max": 0,
      "flare_class": "M",
      "location": "New Orleans",
      "country_code": "us",
      "z_score": 3.6,
      "label": "Rischio rete elevato a New Orleans: combinazione domanda anomala + perturbazione magnetica (Kp=0.5)"
    },
    {
      "grid_stress_score": 5.41,
      "geo_component": 0.21,
      "solar_component": 1.2,
      "energy_component": 4.0,
      "risk_level": "HIGH",
      "kp_current": 0.47,
      "kp_forecast_max": 0,
      "flare_class": "M",
      "location": "Nashville",
      "country_code": "us",
      "z_score": 3.39,
      "label": "Rischio rete elevato a Nashville: combinazione domanda anomala + perturbazione magnetica (Kp=0.5)"
    },
    {
      "grid_stress_score": 5.41,
      "geo_component": 0.21,
      "solar_component": 1.2,
      "energy_component": 4.0,
      "risk_level": "HIGH",
      "kp_current": 0.47,
      "kp_forecast_max": 0,
      "flare_class": "M",
      "location": "Phoenix",
      "country_code": "us",
      "z_score": 3.3,
      "label": "Rischio rete elevato a Phoenix: combinazione domanda anomala + perturbazione magnetica (Kp=0.5)"
    },
    {
      "grid_stress_score": 5.41,
      "geo_component": 0.21,
      "solar_component": 1.2,
      "energy_component": 4.0,
      "risk_level": "HIGH",
      "kp_current": 0.47,
      "kp_forecast_max": 0,
      "flare_class": "M",
      "location": "Tucson",
      "country_code": "us",
      "z_score": 3.73,
      "label": "Rischio rete elevato a Tucson: combinazione domanda anomala + perturbazione magnetica (Kp=0.5)"
    },
    {
      "grid_stress_score": 5.41,
      "geo_component": 0.21,
      "solar_component": 1.2,
      "energy_component": 4.0,
      "risk_level": "HIGH",
      "kp_current": 0.47,
      "kp_forecast_max": 0,
      "flare_class": "M",
      "location": "Calgary",
      "country_code": "ca",
      "z_score": -3.38,
      "label": "Rischio rete elevato a Calgary: combinazione domanda anomala + perturbazione magnetica (Kp=0.5)"
    }
  ],
  "total_nodes": 30
}