{
  "timestamp": "2026-05-20T02:54:32.456167+00:00",
  "space_weather": {
    "timestamp": "2026-05-20T02:54:32.180282+00:00",
    "kp_current": 3.0,
    "kp_forecast_max_24h": 0,
    "solar_flux": 8.588061177761119e-07,
    "flare_class": "C",
    "storm_probability": {
      "G1": 0,
      "G2": 0,
      "G3": 0
    },
    "kp_forecast": []
  },
  "grid_stress": [
    {
      "grid_stress_score": 5.83,
      "geo_component": 1.33,
      "solar_component": 0.5,
      "energy_component": 4.0,
      "risk_level": "HIGH",
      "kp_current": 3.0,
      "kp_forecast_max": 0,
      "flare_class": "C",
      "location": "Saylac",
      "country_code": "eu",
      "z_score": 3.66,
      "label": "Rischio rete elevato a Saylac: combinazione domanda anomala + perturbazione magnetica (Kp=3.0)"
    },
    {
      "grid_stress_score": 5.83,
      "geo_component": 1.33,
      "solar_component": 0.5,
      "energy_component": 4.0,
      "risk_level": "HIGH",
      "kp_current": 3.0,
      "kp_forecast_max": 0,
      "flare_class": "C",
      "location": "Zacatecoluca",
      "country_code": "eu",
      "z_score": 4.4,
      "label": "Rischio rete elevato a Zacatecoluca: combinazione domanda anomala + perturbazione magnetica (Kp=3.0)"
    },
    {
      "grid_stress_score": 5.83,
      "geo_component": 1.33,
      "solar_component": 0.5,
      "energy_component": 4.0,
      "risk_level": "HIGH",
      "kp_current": 3.0,
      "kp_forecast_max": 0,
      "flare_class": "C",
      "location": "Usulután",
      "country_code": "eu",
      "z_score": 4.43,
      "label": "Rischio rete elevato a Usulután: combinazione domanda anomala + perturbazione magnetica (Kp=3.0)"
    },
    {
      "grid_stress_score": 5.83,
      "geo_component": 1.33,
      "solar_component": 0.5,
      "energy_component": 4.0,
      "risk_level": "HIGH",
      "kp_current": 3.0,
      "kp_forecast_max": 0,
      "flare_class": "C",
      "location": "Soyapango",
      "country_code": "eu",
      "z_score": 3.63,
      "label": "Rischio rete elevato a Soyapango: combinazione domanda anomala + perturbazione magnetica (Kp=3.0)"
    },
    {
      "grid_stress_score": 5.83,
      "geo_component": 1.33,
      "solar_component": 0.5,
      "energy_component": 4.0,
      "risk_level": "HIGH",
      "kp_current": 3.0,
      "kp_forecast_max": 0,
      "flare_class": "C",
      "location": "Sonzacate",
      "country_code": "eu",
      "z_score": 3.34,
      "label": "Rischio rete elevato a Sonzacate: combinazione domanda anomala + perturbazione magnetica (Kp=3.0)"
    },
    {
      "grid_stress_score": 5.83,
      "geo_component": 1.33,
      "solar_component": 0.5,
      "energy_component": 4.0,
      "risk_level": "HIGH",
      "kp_current": 3.0,
      "kp_forecast_max": 0,
      "flare_class": "C",
      "location": "Sonsonate",
      "country_code": "eu",
      "z_score": 4.11,
      "label": "Rischio rete elevato a Sonsonate: combinazione domanda anomala + perturbazione magnetica (Kp=3.0)"
    },
    {
      "grid_stress_score": 5.83,
      "geo_component": 1.33,
      "solar_component": 0.5,
      "energy_component": 4.0,
      "risk_level": "HIGH",
      "kp_current": 3.0,
      "kp_forecast_max": 0,
      "flare_class": "C",
      "location": "Iriba",
      "country_code": "eu",
      "z_score": 3.77,
      "label": "Rischio rete elevato a Iriba: combinazione domanda anomala + perturbazione magnetica (Kp=3.0)"
    },
    {
      "grid_stress_score": 5.83,
      "geo_component": 1.33,
      "solar_component": 0.5,
      "energy_component": 4.0,
      "risk_level": "HIGH",
      "kp_current": 3.0,
      "kp_forecast_max": 0,
      "flare_class": "C",
      "location": "Goz Beida",
      "country_code": "eu",
      "z_score": 3.66,
      "label": "Rischio rete elevato a Goz Beida: combinazione domanda anomala + perturbazione magnetica (Kp=3.0)"
    },
    {
      "grid_stress_score": 5.83,
      "geo_component": 1.33,
      "solar_component": 0.5,
      "energy_component": 4.0,
      "risk_level": "HIGH",
      "kp_current": 3.0,
      "kp_forecast_max": 0,
      "flare_class": "C",
      "location": "Fada",
      "country_code": "eu",
      "z_score": 5.03,
      "label": "Rischio rete elevato a Fada: combinazione domanda anomala + perturbazione magnetica (Kp=3.0)"
    },
    {
      "grid_stress_score": 5.83,
      "geo_component": 1.33,
      "solar_component": 0.5,
      "energy_component": 4.0,
      "risk_level": "HIGH",
      "kp_current": 3.0,
      "kp_forecast_max": 0,
      "flare_class": "C",
      "location": "Biltine",
      "country_code": "eu",
      "z_score": 4.34,
      "label": "Rischio rete elevato a Biltine: combinazione domanda anomala + perturbazione magnetica (Kp=3.0)"
    },
    {
      "grid_stress_score": 5.83,
      "geo_component": 1.33,
      "solar_component": 0.5,
      "energy_component": 4.0,
      "risk_level": "HIGH",
      "kp_current": 3.0,
      "kp_forecast_max": 0,
      "flare_class": "C",
      "location": "Am Timan",
      "country_code": "eu",
      "z_score": 3.2,
      "label": "Rischio rete elevato a Am Timan: combinazione domanda anomala + perturbazione magnetica (Kp=3.0)"
    },
    {
      "grid_stress_score": 5.83,
      "geo_component": 1.33,
      "solar_component": 0.5,
      "energy_component": 4.0,
      "risk_level": "HIGH",
      "kp_current": 3.0,
      "kp_forecast_max": 0,
      "flare_class": "C",
      "location": "Patnos",
      "country_code": "tr",
      "z_score": -3.06,
      "label": "Rischio rete elevato a Patnos: combinazione domanda anomala + perturbazione magnetica (Kp=3.0)"
    },
    {
      "grid_stress_score": 5.83,
      "geo_component": 1.33,
      "solar_component": 0.5,
      "energy_component": 4.0,
      "risk_level": "HIGH",
      "kp_current": 3.0,
      "kp_forecast_max": 0,
      "flare_class": "C",
      "location": "Fort Hunt",
      "country_code": "us",
      "z_score": 5.2,
      "label": "Rischio rete elevato a Fort Hunt: combinazione domanda anomala + perturbazione magnetica (Kp=3.0)"
    },
    {
      "grid_stress_score": 5.83,
      "geo_component": 1.33,
      "solar_component": 0.5,
      "energy_component": 4.0,
      "risk_level": "HIGH",
      "kp_current": 3.0,
      "kp_forecast_max": 0,
      "flare_class": "C",
      "location": "Bessemer",
      "country_code": "us",
      "z_score": 4.43,
      "label": "Rischio rete elevato a Bessemer: combinazione domanda anomala + perturbazione magnetica (Kp=3.0)"
    },
    {
      "grid_stress_score": 5.83,
      "geo_component": 1.33,
      "solar_component": 0.5,
      "energy_component": 4.0,
      "risk_level": "HIGH",
      "kp_current": 3.0,
      "kp_forecast_max": 0,
      "flare_class": "C",
      "location": "Paducah",
      "country_code": "us",
      "z_score": 3.86,
      "label": "Rischio rete elevato a Paducah: combinazione domanda anomala + perturbazione magnetica (Kp=3.0)"
    },
    {
      "grid_stress_score": 5.83,
      "geo_component": 1.33,
      "solar_component": 0.5,
      "energy_component": 4.0,
      "risk_level": "HIGH",
      "kp_current": 3.0,
      "kp_forecast_max": 0,
      "flare_class": "C",
      "location": "Cordova",
      "country_code": "us",
      "z_score": 4.17,
      "label": "Rischio rete elevato a Cordova: combinazione domanda anomala + perturbazione magnetica (Kp=3.0)"
    },
    {
      "grid_stress_score": 5.83,
      "geo_component": 1.33,
      "solar_component": 0.5,
      "energy_component": 4.0,
      "risk_level": "HIGH",
      "kp_current": 3.0,
      "kp_forecast_max": 0,
      "flare_class": "C",
      "location": "Center Point",
      "country_code": "us",
      "z_score": 3.94,
      "label": "Rischio rete elevato a Center Point: combinazione domanda anomala + perturbazione magnetica (Kp=3.0)"
    },
    {
      "grid_stress_score": 5.83,
      "geo_component": 1.33,
      "solar_component": 0.5,
      "energy_component": 4.0,
      "risk_level": "HIGH",
      "kp_current": 3.0,
      "kp_forecast_max": 0,
      "flare_class": "C",
      "location": "Cullman",
      "country_code": "us",
      "z_score": 3.77,
      "label": "Rischio rete elevato a Cullman: combinazione domanda anomala + perturbazione magnetica (Kp=3.0)"
    },
    {
      "grid_stress_score": 5.83,
      "geo_component": 1.33,
      "solar_component": 0.5,
      "energy_component": 4.0,
      "risk_level": "HIGH",
      "kp_current": 3.0,
      "kp_forecast_max": 0,
      "flare_class": "C",
      "location": "Daphne",
      "country_code": "us",
      "z_score": 3.66,
      "label": "Rischio rete elevato a Daphne: combinazione domanda anomala + perturbazione magnetica (Kp=3.0)"
    },
    {
      "grid_stress_score": 5.83,
      "geo_component": 1.33,
      "solar_component": 0.5,
      "energy_component": 4.0,
      "risk_level": "HIGH",
      "kp_current": 3.0,
      "kp_forecast_max": 0,
      "flare_class": "C",
      "location": "Decatur",
      "country_code": "us",
      "z_score": 4.26,
      "label": "Rischio rete elevato a Decatur: combinazione domanda anomala + perturbazione magnetica (Kp=3.0)"
    }
  ],
  "total_nodes": 30
}