{
  "timestamp": "2026-04-16T21:39:53.844606+00:00",
  "space_weather": {
    "timestamp": "2026-04-16T21:39:53.496551+00:00",
    "kp_current": 0.0,
    "kp_forecast_max_24h": 0,
    "solar_flux": 0.0,
    "flare_class": "A",
    "storm_probability": {
      "G1": 0,
      "G2": 0,
      "G3": 0
    },
    "kp_forecast": []
  },
  "grid_stress": [
    {
      "grid_stress_score": 4.0,
      "geo_component": 0.0,
      "solar_component": 0,
      "energy_component": 4.0,
      "risk_level": "MODERATE",
      "kp_current": 0.0,
      "kp_forecast_max": 0,
      "flare_class": "A",
      "location": "Bilbao",
      "country_code": "es",
      "z_score": 3.85,
      "label": "Attenzione rete a Bilbao: condizioni di stress moderate — monitorare nelle prossime 6h"
    },
    {
      "grid_stress_score": 3.24,
      "geo_component": 0.0,
      "solar_component": 0,
      "energy_component": 3.24,
      "risk_level": "MODERATE",
      "kp_current": 0.0,
      "kp_forecast_max": 0,
      "flare_class": "A",
      "location": "Torino",
      "country_code": "it",
      "z_score": 2.43,
      "label": "Attenzione rete a Torino: condizioni di stress moderate — monitorare nelle prossime 6h"
    },
    {
      "grid_stress_score": 3.13,
      "geo_component": 0.0,
      "solar_component": 0,
      "energy_component": 3.13,
      "risk_level": "MODERATE",
      "kp_current": 0.0,
      "kp_forecast_max": 0,
      "flare_class": "A",
      "location": "Stavanger",
      "country_code": "no",
      "z_score": 2.35,
      "label": "Attenzione rete a Stavanger: condizioni di stress moderate — monitorare nelle prossime 6h"
    },
    {
      "grid_stress_score": 2.24,
      "geo_component": 0.0,
      "solar_component": 0,
      "energy_component": 2.24,
      "risk_level": "LOW",
      "kp_current": 0.0,
      "kp_forecast_max": 0,
      "flare_class": "A",
      "location": "Venezia",
      "country_code": "it",
      "z_score": 1.68,
      "label": "Rete stabile a Venezia: nessuna perturbazione geomagnetica significativa"
    },
    {
      "grid_stress_score": 1.55,
      "geo_component": 0.0,
      "solar_component": 0,
      "energy_component": 1.55,
      "risk_level": "LOW",
      "kp_current": 0.0,
      "kp_forecast_max": 0,
      "flare_class": "A",
      "location": "Rimini",
      "country_code": "it",
      "z_score": 1.16,
      "label": "Rete stabile a Rimini: nessuna perturbazione geomagnetica significativa"
    },
    {
      "grid_stress_score": 1.31,
      "geo_component": 0.0,
      "solar_component": 0,
      "energy_component": 1.31,
      "risk_level": "LOW",
      "kp_current": 0.0,
      "kp_forecast_max": 0,
      "flare_class": "A",
      "location": "Varese",
      "country_code": "it",
      "z_score": 0.98,
      "label": "Rete stabile a Varese: nessuna perturbazione geomagnetica significativa"
    },
    {
      "grid_stress_score": 1.15,
      "geo_component": 0.0,
      "solar_component": 0,
      "energy_component": 1.15,
      "risk_level": "LOW",
      "kp_current": 0.0,
      "kp_forecast_max": 0,
      "flare_class": "A",
      "location": "Trondheim",
      "country_code": "no",
      "z_score": -0.86,
      "label": "Rete stabile a Trondheim: nessuna perturbazione geomagnetica significativa"
    },
    {
      "grid_stress_score": 1.03,
      "geo_component": 0.0,
      "solar_component": 0,
      "energy_component": 1.03,
      "risk_level": "LOW",
      "kp_current": 0.0,
      "kp_forecast_max": 0,
      "flare_class": "A",
      "location": "Amsterdam",
      "country_code": "nl",
      "z_score": 0.77,
      "label": "Rete stabile a Amsterdam: nessuna perturbazione geomagnetica significativa"
    },
    {
      "grid_stress_score": 0.64,
      "geo_component": 0.0,
      "solar_component": 0,
      "energy_component": 0.64,
      "risk_level": "LOW",
      "kp_current": 0.0,
      "kp_forecast_max": 0,
      "flare_class": "A",
      "location": "Ancona",
      "country_code": "it",
      "z_score": 0.48,
      "label": "Rete stabile a Ancona: nessuna perturbazione geomagnetica significativa"
    },
    {
      "grid_stress_score": 0.43,
      "geo_component": 0.0,
      "solar_component": 0,
      "energy_component": 0.43,
      "risk_level": "LOW",
      "kp_current": 0.0,
      "kp_forecast_max": 0,
      "flare_class": "A",
      "location": "Potenza",
      "country_code": "it",
      "z_score": 0.32,
      "label": "Rete stabile a Potenza: nessuna perturbazione geomagnetica significativa"
    }
  ],
  "total_nodes": 10
}