{
  "slug": "2026-05-24-durgapur-cold-snap",
  "title": "Durgapur Cold Snap",
  "lead": "Durgapur is experiencing a cold snap with a Z-Score of -1.50. This unusual event has a score of 5.0/10.",
  "body": "The current weather conditions in Durgapur are characterized by a significant drop in temperature, resulting in a Heating Degree Day (HDD) value of 3.0 GG.\n The humidity level is at 60%, with no wind, as indicated by a wind speed of 0.0 km/h.\n The absence of Cooling Degree Days (CDD) with a value of 0.0 GG further emphasizes the cold conditions.",
  "conclusion": "Monitor the situation for further updates.",
  "agri_impact": "Crops may be damaged",
  "logistica_impact": "Transport delayed",
  "energia_impact": "Heating demand increased",
  "cover_url": "",
  "location": "Durgāpur",
  "country_code": "in",
  "vertical": "cold-snap",
  "z_score": -1.5,
  "score": 5.0,
  "anomaly_level": "UNUSUAL",
  "hdd": 3.0,
  "cdd": 0,
  "hdd_delta": 2.0,
  "humidity_pct": 60,
  "wind_kmh": 0.0,
  "timestamp": "2026-05-24T02:49:11.577087+00:00",
  "date": "2026-05-24"
}