{
  "slug": "2026-05-23-plato-heavy-rain",
  "title": "Pioggia intensa a Plato",
  "lead": "La citta di Plato sta sperimentando una pioggia intensa anomala con un Z-Score di +3.09. Il livello di allerta e' critico.",
  "body": "La pioggia intensa a Plato ha causato un aumento dell'umidita' dell'87%. \n La velocita' del vento e' molto bassa a 1.9 km/h. \n La temperatura non sembra essere influenzata da questo evento.",
  "conclusion": "E' necessario monitorare la situazione meteo per eventuali aggiornamenti.",
  "agri_impact": "Pericolo per le colture",
  "logistica_impact": "Difficolta' di trasporto",
  "energia_impact": "Riduzione della domanda",
  "cover_url": "",
  "location": "Plato",
  "country_code": "co",
  "vertical": "heavy-rain",
  "z_score": 3.09,
  "score": 10.0,
  "anomaly_level": "CRITICAL",
  "hdd": 0,
  "cdd": 9.8,
  "hdd_delta": -1.0,
  "humidity_pct": 87,
  "wind_kmh": 1.9,
  "timestamp": "2026-05-23T09:47:41.365784+00:00",
  "date": "2026-05-23"
}