{
  "slug": "2026-05-16-montelimar-heavy-rain",
  "title": "Montelimar heavy rain",
  "lead": "Montelimar sta sperimentando piogge intense con uno Z-Score di -3.06. Le condizioni meteo sono critiche.",
  "body": "La citta di Montelimar sta registrando piogge abbondanti con un tasso di umidita dell'87%. \n La velocita del vento e di 9.3 km/h, il che non aiuta a migliorare la situazione. \n Le condizioni meteo sono previste per rimanere critiche con un livello di allarme alto.",
  "conclusion": "E' necessario adottare misure di sicurezza immediate.",
  "agri_impact": "Danni alle colture",
  "logistica_impact": "Interruzioni nel traffico",
  "energia_impact": "Possibili black out",
  "cover_url": "",
  "location": "Montélimar",
  "country_code": "fr",
  "vertical": "heavy-rain",
  "z_score": -3.06,
  "score": 10.0,
  "anomaly_level": "CRITICAL",
  "hdd": 11.7,
  "cdd": 0,
  "hdd_delta": 10.7,
  "humidity_pct": 87,
  "wind_kmh": 9.3,
  "timestamp": "2026-05-16T02:33:45.131710+00:00",
  "date": "2026-05-16"
}